napari_stress/__init__.py
napari_stress/_napari_plugin.py
napari_stress/_preprocess.py
napari_stress/_surface.py
napari_stress/_vectors.py
napari_stress/_version.py
napari_stress/napari.yaml
napari_stress/types.py
napari_stress/_approximation/__init__.py
napari_stress/_approximation/expansion.py
napari_stress/_approximation/expansion_base.py
napari_stress/_approximation/expansion_napari.py
napari_stress/_approximation/fit_ellipsoid.py
napari_stress/_measurements/__init__.py
napari_stress/_measurements/curvature.py
napari_stress/_measurements/deviation_analysis.py
napari_stress/_measurements/geodesics.py
napari_stress/_measurements/intensity.py
napari_stress/_measurements/measurements.py
napari_stress/_measurements/stresses.py
napari_stress/_measurements/temporal_correlation.py
napari_stress/_measurements/toolbox.py
napari_stress/_measurements/toolbox.ui
napari_stress/_plotting/__init__.py
napari_stress/_plotting/create_plots.py
napari_stress/_reconstruction/__init__.py
napari_stress/_reconstruction/fit_utils.py
napari_stress/_reconstruction/patches.py
napari_stress/_reconstruction/reconstruct_surface.py
napari_stress/_reconstruction/refine_surfaces.py
napari_stress/_reconstruction/toolbox.py
napari_stress/_reconstruction/toolbox.ui
napari_stress/_sample_data/ExampleTifSequence.tif
napari_stress/_sample_data/__init__.py
napari_stress/_sample_data/dropplet_point_cloud.csv
napari_stress/_sample_data/dropplet_point_cloud_4d.csv
napari_stress/_sample_data/sample_data.py
napari_stress/_spherical_harmonics/__init__.py
napari_stress/_spherical_harmonics/fit_utils.py
napari_stress/_spherical_harmonics/spherical_harmonics.py
napari_stress/_spherical_harmonics/spherical_harmonics_napari.py
napari_stress/_spherical_harmonics/Pickled_LBDV_Files/LBDV_Basis_at_Quad_Pts_Deg_basis5_Quad_Pts434
napari_stress/_spherical_harmonics/Pickled_LBDV_Files/LBDV_Basis_at_Quad_Pts_Deg_basis5_Quad_Pts50
napari_stress-0.4.2.dist-info/licenses/LICENSE
napari_stress-0.4.2.dist-info/METADATA
napari_stress-0.4.2.dist-info/WHEEL
napari_stress-0.4.2.dist-info/entry_points.txt
napari_stress-0.4.2.dist-info/top_level.txt
napari_stress-0.4.2.dist-info/RECORD
