Metadata-Version: 2.4
Name: napari-stress
Version: 0.4.2
Summary: Interactive surface analysis in napari for measuring mechanical stresses in biological tissues
Author: Johannes Soltwedel, Ben J. Gross, Elijah Shelton, Carlos Gomez, Otger Campas
Author-email: johannes_richard.mueller@tu-dresden.de
License: Copyright (c) 2022, Johannes Müller, DFG Cluster of Excellence "Physics of Life", TU Dresden, Dresden, Germany & The Regents of the University of California
Project-URL: Bug Tracker, https://github.com/campaslab/napari-stress/issues
Project-URL: Documentation, https://campaslab.github.io/napari-stress
Project-URL: Source Code, https://github.com/campaslab/napari-stress
Project-URL: User Support, https://github.com/campaslab/napari-stress/issues
Classifier: Development Status :: 2 - Pre-Alpha
Classifier: Framework :: napari
Classifier: Intended Audience :: Developers
Classifier: License :: OSI Approved :: BSD License
Classifier: Operating System :: OS Independent
Classifier: Programming Language :: Python
Classifier: Programming Language :: Python :: 3
Classifier: Programming Language :: Python :: 3 :: Only
Classifier: Programming Language :: Python :: 3.9
Classifier: Programming Language :: Python :: 3.10
Classifier: Programming Language :: Python :: 3.11
Classifier: Topic :: Software Development :: Testing
Requires-Python: >=3.9
License-File: LICENSE
Requires-Dist: dask
Requires-Dist: distributed
Requires-Dist: joblib
Requires-Dist: mpmath
Requires-Dist: napari
Requires-Dist: napari-tools-menu>=0.1.15
Requires-Dist: numpy<2.0.0
Requires-Dist: pandas
Requires-Dist: scikit-image
Requires-Dist: scipy>=1.9.0
Requires-Dist: seaborn
Requires-Dist: tqdm
Requires-Dist: napari-vedo-bridge>=0.2.2
Requires-Dist: vedo>=2023.5.0
Requires-Dist: vispy
Requires-Dist: deprecation
Requires-Dist: gdist
Requires-Dist: pygeodesic
Provides-Extra: testing
Requires-Dist: tox; extra == "testing"
Requires-Dist: pytest; extra == "testing"
Requires-Dist: pytest-cov; extra == "testing"
Requires-Dist: pytest-qt; extra == "testing"
Requires-Dist: pyqt5; extra == "testing"
Dynamic: license-file
